python_cassandra_jaeger/__init__.py
python_cassandra_jaeger-0.4.dist-info/LICENSE
python_cassandra_jaeger-0.4.dist-info/METADATA
python_cassandra_jaeger-0.4.dist-info/WHEEL
python_cassandra_jaeger-0.4.dist-info/top_level.txt
python_cassandra_jaeger-0.4.dist-info/RECORD
