Metadata-Version: 2.1
Name: python-cassandra-jaeger
Version: 0.4
Summary: Library to correctly pass current OpenTracing span to Cassandra
Home-page: https://github.com/piotrmaslanka/python-cassandra-jaeger/
Author: Piotr Maślanka
Author-email: piotr.maslanka@henrietta.com.pl
License: UNKNOWN
Project-URL: Code, https://github.com/piotrmaslanka/python-cassandra-jaeger
Project-URL: Issue tracker, https://github.com/piotrmaslanka/python-cassandra-jaeger/issues
Keywords: cassandra,cassandra-driver,jaeger,opentracing,tracing
Platform: UNKNOWN
Classifier: Programming Language :: Python
Classifier: Programming Language :: Python :: 3.5
Classifier: Programming Language :: Python :: 3.6
Classifier: Programming Language :: Python :: 3.7
Classifier: Programming Language :: Python :: 3.8
Classifier: Programming Language :: Python :: 3.9
Classifier: Programming Language :: Python :: Implementation :: CPython
Classifier: Programming Language :: Python :: Implementation :: PyPy
Classifier: Operating System :: POSIX
Classifier: Operating System :: OS Independent
Classifier: Development Status :: 5 - Production/Stable
Classifier: License :: OSI Approved :: MIT License
Classifier: Topic :: Software Development :: Libraries
Requires-Python: !=2.7.*,!=3.0.*,!=3.1.*,!=3.2.*,!=3.3.*,!=3.4.*
Requires-Dist: cassandra-driver
Requires-Dist: opentracing
Requires-Dist: satella
